{
  "courses": [
    {
      "name": "Coconut Mall",
      "origin": "Wii",
      "coord": {
        "row": 3,
        "col": 1,
        "pos": 4
      },
      "rank": 1
    },
    {
      "name": "Maple Treeway",
      "origin": "Wii",
      "coord": {
        "row": 3,
        "col": 5,
        "pos": 4
      },
      "rank": 2
    },
    {
      "name": "Moo Moo Meadows",
      "origin": "Wii",
      "coord": {
        "row": 2,
        "col": 1,
        "pos": 1
      },
      "rank": 3
    },
    {
      "name": "Squeaky Clean Sprint",
      "origin": "MK8",
      "coord": {
        "row": 4,
        "col": 3,
        "pos": 4
      },
      "rank": 4
    },
    {
      "name": "Tick Tock Clock",
      "origin": "DS",
      "coord": {
        "row": 2,
        "col": 4,
        "pos": 1
      },
      "rank": 5
    },
    {
      "name": "Peach Gardens",
      "origin": "DS",
      "coord": {
        "row": 3,
        "col": 6,
        "pos": 2
      },
      "rank": 6
    },
    {
      "name": "Moonview Highway",
      "origin": "Wii",
      "coord": {
        "row": 4,
        "col": 3,
        "pos": 3
      },
      "rank": 7
    },
    {
      "name": "DK Summit",
      "origin": "Wii",
      "coord": {
        "row": 4,
        "col": 1,
        "pos": 3
      },
      "rank": 8
    },
    {
      "name": "Ice Ice Outpost",
      "origin": "MK8",
      "coord": {
        "row": 2,
        "col": 5,
        "pos": 3
      },
      "rank": 9
    },
    {
      "name": "Rock Rock Mountain",
      "origin": "TDS",
      "coord": {
        "row": 3,
        "col": 5,
        "pos": 3
      },
      "rank": 10
    },
    {
      "name": "Sherbet Land",
      "origin": "GCN",
      "coord": {
        "row": 2,
        "col": 3,
        "pos": 2
      },
      "rank": 11
    },
    {
      "name": "Sky-High Sundae",
      "origin": "MK8",
      "coord": {
        "row": 3,
        "col": 4,
        "pos": 4
      },
      "rank": 12
    },
    {
      "name": "Cloudtop Cruise",
      "origin": "MK8",
      "coord": {
        "row": 1,
        "col": 4,
        "pos": 1
      },
      "rank": 13
    },
    {
      "name": "Waluigi Pinball",
      "origin": "DS",
      "coord": {
        "row": 3,
        "col": 3,
        "pos": 4
      },
      "rank": 14
    },
    {
      "name": "Rainbow Road",
      "origin": "N64",
      "coord": {
        "row": 2,
        "col": 4,
        "pos": 4
      },
      "rank": 15
    },
    {
      "name": "Rainbow Road",
      "origin": "Wii",
      "coord": {
        "row": 4,
        "col": 6,
        "pos": 4
      },
      "rank": 16
    },
    {
      "name": "Koopa Cape",
      "origin": "Wii",
      "coord": {
        "row": 4,
        "col": 4,
        "pos": 3
      },
      "rank": 17
    },
    {
      "name": "Music Park",
      "origin": "TDS",
      "coord": {
        "row": 2,
        "col": 3,
        "pos": 3
      },
      "rank": 18
    },
    {
      "name": "Yoshi Valley",
      "origin": "N64",
      "coord": {
        "row": 2,
        "col": 3,
        "pos": 4
      },
      "rank": 19
    },
    {
      "name": "Mushroom Gorge",
      "origin": "Wii",
      "coord": {
        "row": 3,
        "col": 4,
        "pos": 3
      },
      "rank": 20
    },
    {
      "name": "Mount Wario",
      "origin": "MK8",
      "coord": {
        "row": 1,
        "col": 3,
        "pos": 4
      },
      "rank": 21
    },
    {
      "name": "Sunshine Airport",
      "origin": "MK8",
      "coord": {
        "row": 1,
        "col": 3,
        "pos": 1
      },
      "rank": 22
    },
    {
      "name": "Toad's Turnpike",
      "origin": "N64",
      "coord": {
        "row": 2,
        "col": 1,
        "pos": 4
      },
      "rank": 23
    },
    {
      "name": "Electrodrome",
      "origin": "MK8",
      "coord": {
        "row": 1,
        "col": 3,
        "pos": 3
      },
      "rank": 24
    },
    {
      "name": "Shroom Ridge",
      "origin": "DS",
      "coord": {
        "row": 3,
        "col": 2,
        "pos": 2
      },
      "rank": 25
    },
    {
      "name": "Rainbow Road",
      "origin": "TDS",
      "coord": {
        "row": 3,
        "col": 6,
        "pos": 4
      },
      "rank": 26
    },
    {
      "name": "Wario's Gold Mine",
      "origin": "Wii",
      "coord": {
        "row": 2,
        "col": 5,
        "pos": 1
      },
      "rank": 27
    },
    {
      "name": "Kalimari Desert",
      "origin": "N64",
      "coord": {
        "row": 3,
        "col": 3,
        "pos": 3
      },
      "rank": 28
    },
    {
      "name": "Daisy Circuit",
      "origin": "Wii",
      "coord": {
        "row": 4,
        "col": 5,
        "pos": 3
      },
      "rank": 29
    },
    {
      "name": "Daisy Cruiser",
      "origin": "GCN",
      "coord": {
        "row": 4,
        "col": 3,
        "pos": 2
      },
      "rank": 30
    },
    {
      "name": "Sky Garden",
      "origin": "GBA",
      "coord": {
        "row": 3,
        "col": 2,
        "pos": 3
      },
      "rank": 31
    },
    {
      "name": "Bowser's Castle",
      "origin": "MK8",
      "coord": {
        "row": 1,
        "col": 4,
        "pos": 3
      },
      "rank": 32
    },
    {
      "name": "Ninja Hideaway",
      "origin": "Tour",
      "coord": {
        "row": 3,
        "col": 2,
        "pos": 4
      },
      "rank": 33
    },
    {
      "name": "Big Blue",
      "origin": "MK8",
      "coord": {
        "row": 2,
        "col": 6,
        "pos": 4
      },
      "rank": 34
    },
    {
      "name": "Toad Harbor",
      "origin": "MK8",
      "coord": {
        "row": 1,
        "col": 2,
        "pos": 2
      },
      "rank": 35
    },
    {
      "name": "Mute City",
      "origin": "MK8",
      "coord": {
        "row": 1,
        "col": 5,
        "pos": 4
      },
      "rank": 36
    },
    {
      "name": "Super Bell Subway",
      "origin": "MK8",
      "coord": {
        "row": 2,
        "col": 6,
        "pos": 3
      },
      "rank": 37
    },
    {
      "name": "DK Mountain",
      "origin": "GCN",
      "coord": {
        "row": 4,
        "col": 5,
        "pos": 2
      },
      "rank": 38
    },
    {
      "name": "Thwomp Ruins",
      "origin": "MK8",
      "coord": {
        "row": 1,
        "col": 1,
        "pos": 4
      },
      "rank": 39
    },
    {
      "name": "Rosalina's Ice World",
      "origin": "TDS",
      "coord": {
        "row": 4,
        "col": 6,
        "pos": 2
      },
      "rank": 40
    },
    {
      "name": "Wild Woods",
      "origin": "MK8",
      "coord": {
        "row": 1,
        "col": 6,
        "pos": 3
      },
      "rank": 41
    },
    {
      "name": "Yoshi's Island",
      "origin": "MK8",
      "coord": {
        "row": 4,
        "col": 1,
        "pos": 4
      },
      "rank": 42
    },
    {
      "name": "Piranha Plant Slide",
      "origin": "TDS",
      "coord": {
        "row": 2,
        "col": 4,
        "pos": 2
      },
      "rank": 43
    },
    {
      "name": "Cheep Cheep Beach",
      "origin": "DS",
      "coord": {
        "row": 2,
        "col": 1,
        "pos": 3
      },
      "rank": 44
    },
    {
      "name": "Hyrule Circuit",
      "origin": "MK8",
      "coord": {
        "row": 2,
        "col": 5,
        "pos": 4
      },
      "rank": 45
    },
    {
      "name": "Grumble Volcano",
      "origin": "Wii",
      "coord": {
        "row": 2,
        "col": 4,
        "pos": 3
      },
      "rank": 46
    },
    {
      "name": "Dragon Driftway",
      "origin": "MK8",
      "coord": {
        "row": 1,
        "col": 5,
        "pos": 3
      },
      "rank": 47
    },
    {
      "name": "Rainbow Road",
      "origin": "MK8",
      "coord": {
        "row": 1,
        "col": 4,
        "pos": 4
      },
      "rank": 48
    },
    {
      "name": "Merry Mountain",
      "origin": "Tour",
      "coord": {
        "row": 3,
        "col": 6,
        "pos": 3
      },
      "rank": 49
    },
    {
      "name": "DK Jungle",
      "origin": "TDS",
      "coord": {
        "row": 2,
        "col": 2,
        "pos": 4
      },
      "rank": 50
    },
    {
      "name": "Toad Circuit",
      "origin": "TDS",
      "coord": {
        "row": 3,
        "col": 1,
        "pos": 2
      },
      "rank": 51
    },
    {
      "name": "Dolphin Shoals",
      "origin": "MK8",
      "coord": {
        "row": 1,
        "col": 3,
        "pos": 2
      },
      "rank": 52
    },
    {
      "name": "Waluigi Stadium",
      "origin": "GCN",
      "coord": {
        "row": 4,
        "col": 2,
        "pos": 3
      },
      "rank": 53
    },
    {
      "name": "Water Park",
      "origin": "MK8",
      "coord": {
        "row": 1,
        "col": 1,
        "pos": 2
      },
      "rank": 54
    },
    {
      "name": "Royal Raceway",
      "origin": "N64",
      "coord": {
        "row": 2,
        "col": 2,
        "pos": 3
      },
      "rank": 55
    },
    {
      "name": "Bangkok Rush",
      "origin": "Tour",
      "coord": {
        "row": 4,
        "col": 2,
        "pos": 1
      },
      "rank": 56
    },
    {
      "name": "Twisted Mansion",
      "origin": "MK8",
      "coord": {
        "row": 1,
        "col": 2,
        "pos": 3
      },
      "rank": 57
    },
    {
      "name": "Snow Land",
      "origin": "GBA",
      "coord": {
        "row": 3,
        "col": 4,
        "pos": 2
      },
      "rank": 58
    },
    {
      "name": "Shy Guy Falls",
      "origin": "MK8",
      "coord": {
        "row": 1,
        "col": 2,
        "pos": 4
      },
      "rank": 59
    },
    {
      "name": "Piranha Plant Cove",
      "origin": "MK8",
      "coord": {
        "row": 4,
        "col": 5,
        "pos": 4
      },
      "rank": 60
    },
    {
      "name": "Ribbon Road",
      "origin": "GBA",
      "coord": {
        "row": 2,
        "col": 6,
        "pos": 2
      },
      "rank": 61
    },
    {
      "name": "Madrid Drive",
      "origin": "Tour",
      "coord": {
        "row": 4,
        "col": 6,
        "pos": 1
      },
      "rank": 62
    },
    {
      "name": "Singapore Speedway",
      "origin": "Tour",
      "coord": {
        "row": 4,
        "col": 2,
        "pos": 4
      },
      "rank": 63
    },
    {
      "name": "Bowser's Castle 3",
      "origin": "SNES",
      "coord": {
        "row": 4,
        "col": 6,
        "pos": 3
      },
      "rank": 64
    },
    {
      "name": "Vancouver Velocity",
      "origin": "Tour",
      "coord": {
        "row": 4,
        "col": 4,
        "pos": 4
      },
      "rank": 65
    },
    {
      "name": "Excitebike Arena",
      "origin": "MK8",
      "coord": {
        "row": 1,
        "col": 5,
        "pos": 2
      },
      "rank": 66
    },
    {
      "name": "Animal Crossing Circuit",
      "origin": "MK8",
      "coord": {
        "row": 1,
        "col": 6,
        "pos": 4
      },
      "rank": 67
    },
    {
      "name": "Sweet Sweet Canyon",
      "origin": "MK8",
      "coord": {
        "row": 1,
        "col": 1,
        "pos": 3
      },
      "rank": 68
    },
    {
      "name": "New York Minute",
      "origin": "Tour",
      "coord": {
        "row": 3,
        "col": 3,
        "pos": 1
      },
      "rank": 69
    },
    {
      "name": "Mario Kart Stadium",
      "origin": "MK8",
      "coord": {
        "row": 1,
        "col": 1,
        "pos": 1
      },
      "rank": 70
    },
    {
      "name": "Sunset Wilds",
      "origin": "GBA",
      "coord": {
        "row": 4,
        "col": 4,
        "pos": 2
      },
      "rank": 71
    },
    {
      "name": "Rome Avanti",
      "origin": "Tour",
      "coord": {
        "row": 4,
        "col": 5,
        "pos": 1
      },
      "rank": 72
    },
    {
      "name": "Berlin Byways",
      "origin": "Tour",
      "coord": {
        "row": 3,
        "col": 6,
        "pos": 1
      },
      "rank": 73
    },
    {
      "name": "Riverside Park",
      "origin": "GBA",
      "coord": {
        "row": 4,
        "col": 1,
        "pos": 2
      },
      "rank": 74
    },
    {
      "name": "Rainbow Road",
      "origin": "SNES",
      "coord": {
        "row": 2,
        "col": 5,
        "pos": 2
      },
      "rank": 75
    },
    {
      "name": "Paris Promenade",
      "origin": "Tour",
      "coord": {
        "row": 3,
        "col": 1,
        "pos": 1
      },
      "rank": 76
    },
    {
      "name": "Mario Circuit",
      "origin": "MK8",
      "coord": {
        "row": 1,
        "col": 2,
        "pos": 1
      },
      "rank": 77
    },
    {
      "name": "Mario Circuit",
      "origin": "GBA",
      "coord": {
        "row": 2,
        "col": 1,
        "pos": 2
      },
      "rank": 78
    },
    {
      "name": "Mario Circuit 3",
      "origin": "SNES",
      "coord": {
        "row": 3,
        "col": 3,
        "pos": 2
      },
      "rank": 79
    },
    {
      "name": "Mario Circuit",
      "origin": "DS",
      "coord": {
        "row": 4,
        "col": 2,
        "pos": 2
      },
      "rank": 80
    },
    {
      "name": "Boo Lake",
      "origin": "GBA",
      "coord": {
        "row": 3,
        "col": 5,
        "pos": 2
      },
      "rank": 81
    },
    {
      "name": "Dry Dry Desert",
      "origin": "GCN",
      "coord": {
        "row": 2,
        "col": 2,
        "pos": 1
      },
      "rank": 82
    },
    {
      "name": "Athens Dash",
      "origin": "Tour",
      "coord": {
        "row": 4,
        "col": 3,
        "pos": 1
      },
      "rank": 83
    },
    {
      "name": "Choco Mountain",
      "origin": "N64",
      "coord": {
        "row": 3,
        "col": 1,
        "pos": 3
      },
      "rank": 84
    },
    {
      "name": "Donut Plains 3",
      "origin": "SNES",
      "coord": {
        "row": 2,
        "col": 2,
        "pos": 2
      },
      "rank": 85
    },
    {
      "name": "Los Angeles Laps",
      "origin": "Tour",
      "coord": {
        "row": 4,
        "col": 4,
        "pos": 1
      },
      "rank": 86
    },
    {
      "name": "Amsterdam Drift",
      "origin": "Tour",
      "coord": {
        "row": 4,
        "col": 1,
        "pos": 1
      },
      "rank": 87
    },
    {
      "name": "Bone Dry Ruins",
      "origin": "MK8",
      "coord": {
        "row": 1,
        "col": 4,
        "pos": 2
      },
      "rank": 88
    },
    {
      "name": "London Loop",
      "origin": "Tour",
      "coord": {
        "row": 3,
        "col": 5,
        "pos": 1
      },
      "rank": 89
    },
    {
      "name": "Neo Bowser City",
      "origin": "TDS",
      "coord": {
        "row": 2,
        "col": 6,
        "pos": 1
      },
      "rank": 90
    },
    {
      "name": "Wario Stadium",
      "origin": "DS",
      "coord": {
        "row": 2,
        "col": 3,
        "pos": 1
      },
      "rank": 91
    },
    {
      "name": "Yoshi's Circuit",
      "origin": "GCN",
      "coord": {
        "row": 1,
        "col": 5,
        "pos": 1
      },
      "rank": 92
    },
    {
      "name": "Baby Park",
      "origin": "GCN",
      "coord": {
        "row": 1,
        "col": 6,
        "pos": 1
      },
      "rank": 93
    },
    {
      "name": "Sydney Sprint",
      "origin": "Tour",
      "coord": {
        "row": 3,
        "col": 4,
        "pos": 1
      },
      "rank": 94
    },
    {
      "name": "Tokyo Blur",
      "origin": "Tour",
      "coord": {
        "row": 3,
        "col": 2,
        "pos": 1
      },
      "rank": 95
    },
    {
      "name": "Cheese Land",
      "origin": "GBA",
      "coord": {
        "row": 1,
        "col": 6,
        "pos": 2
      },
      "rank": 96
    }
  ],
  "current": [
        0, 1, 2, 3, 4, 5, 6, 7, 8, 9, 10, 11, 12, 13, 14, 15, 16, 17, 18, 19,
        20, 21, 22, 23, 24, 25, 26, 27, 28, 29, 30, 31, 32, 33, 34, 35, 36, 37,
        38, 39, 40, 41, 42, 43, 44, 45, 46, 47, 48, 49, 50, 51, 52, 53, 54, 55,
        56, 57, 58, 59, 60, 61, 62, 63, 64, 65, 66, 67, 68, 69, 70, 71, 72, 73,
        74, 75, 76, 77, 78, 79, 80, 81, 82, 83, 84, 85, 86, 87, 88, 89, 90, 91,
        92, 93, 94, 95
    ],
  "removed": [],
  "save_name": "mk8d.json",
  "history": {
    "past": [],
    "future": []
  }
}
